{
  "audio": "http://download.ted.com/talks/CaitriaONeill_2012X.mp3",
  "author": "Caitria + Morgan O'Neill",
  "dateFilmed": 1340323200,
  "datePublished": 1344956665,
  "description": "After a natural disaster strikes, there’s only a tiny window of opportunity to rally effective recovery efforts before the world turns their attention elsewhere. Who should be in charge? When a freak tornado hit their hometown, sisters Caitria and Morgan O’Neill -- just 20 and 24 at the time -- took the reins and are now teaching others how to do the same. (Filmed at TEDxBoston.)",
  "duration": 563,
  "event": "TEDxBoston 2012",
  "image": "https://pi.tedcdn.com/r/pe.tedcdn.com/images/ted/39b48aeef9bbd8d2a9b55e93ee03c027e2a8f891_2880x1620.jpg",
  "keywords": [
    "TEDx",
    "cooperation",
    "culture",
    "disaster relief",
    "natural disaster",
    "weather"
  ],
  "mainLanguage": null,
  "objectID": 1545,
  "otherLanguages": {
    "ar": "Arabic",
    "zh-cn": "Chinese, Simplified",
    "zh-tw": "Chinese, Traditional",
    "hr": "Croatian",
    "nl": "Dutch",
    "en": "English",
    "fr": "French",
    "de": "German",
    "he": "Hebrew",
    "hu": "Hungarian",
    "it": "Italian",
    "ja": "Japanese",
    "ko": "Korean",
    "nb": "Norwegian Bokmal",
    "pl": "Polish",
    "pt": "Portuguese",
    "pt-br": "Portuguese, Brazilian",
    "ro": "Romanian",
    "ru": "Russian",
    "sr": "Serbian",
    "es": "Spanish",
    "vi": "Vietnamese"
  },
  "ratings": {
    "Jaw-dropping": 23,
    "Persuasive": 63,
    "Courageous": 87,
    "Fascinating": 25,
    "Inspiring": 175,
    "Longwinded": 6,
    "OK": 47,
    "Ingenious": 67,
    "Informative": 87,
    "Confusing": 7,
    "Unconvincing": 9,
    "Funny": 10,
    "Beautiful": 4,
    "Obnoxious": 9
  },
  "slug": "caitria_and_morgan_o_neill_how_to_step_up_in_the_face_of_disaster",
  "thumbnail": "https://pi.tedcdn.com/r/pe.tedcdn.com/images/ted/39b48aeef9bbd8d2a9b55e93ee03c027e2a8f891_2880x1620.jpg?quality=89&w=600",
  "title": "How to step up in the face of disaster",
  "url": "https://www.ted.com/talks/caitria_and_morgan_o_neill_how_to_step_up_in_the_face_of_disaster",
  "video": {
    "low": "http://download.ted.com/talks/CaitriaONeill_2012X-light.mp4",
    "medium": "http://download.ted.com/talks/CaitriaONeill_2012X.mp4",
    "high": "http://download.ted.com/talks/CaitriaONeill_2012X-480p.mp4"
  },
  "viewCount": 734717,
  "year": "2012"
}