{
  "audio": "http://download.ted.com/talks/CharlesHazlewood_2011G.mp3",
  "author": "Charles Hazlewood",
  "dateFilmed": 1310515200,
  "datePublished": 1318001156,
  "description": "Conductor Charles Hazlewood talks about the role of trust in musical leadership -- then shows how it works, as he conducts the Scottish Ensemble onstage. He also shares clips from two musical projects: the opera \"U-Carmen eKhayelitsha\" and the ParaOrchestra.",
  "duration": 1176,
  "event": "TEDGlobal 2011",
  "image": "https://pi.tedcdn.com/r/pe.tedcdn.com/images/ted/0ab896226649f56d65b23c843462fec9a8448e3e_800x600.jpg",
  "keywords": [
    "arts",
    "collaboration",
    "conducting",
    "culture",
    "entertainment",
    "music"
  ],
  "mainLanguage": null,
  "objectID": 1240,
  "otherLanguages": {
    "sq": "Albanian",
    "ar": "Arabic",
    "bg": "Bulgarian",
    "zh-cn": "Chinese, Simplified",
    "zh-tw": "Chinese, Traditional",
    "hr": "Croatian",
    "cs": "Czech",
    "nl": "Dutch",
    "en": "English",
    "fr": "French",
    "fr-ca": "French (Canada)",
    "de": "German",
    "he": "Hebrew",
    "hu": "Hungarian",
    "id": "Indonesian",
    "it": "Italian",
    "ja": "Japanese",
    "ko": "Korean",
    "fa": "Persian",
    "pl": "Polish",
    "pt-br": "Portuguese, Brazilian",
    "ro": "Romanian",
    "ru": "Russian",
    "sr": "Serbian",
    "es": "Spanish",
    "th": "Thai",
    "tr": "Turkish",
    "uk": "Ukrainian",
    "vi": "Vietnamese"
  },
  "ratings": {
    "Courageous": 16,
    "Inspiring": 141,
    "Informative": 30,
    "Beautiful": 167,
    "Persuasive": 33,
    "Fascinating": 75,
    "OK": 25,
    "Unconvincing": 16,
    "Funny": 17,
    "Jaw-dropping": 15,
    "Ingenious": 26,
    "Obnoxious": 9,
    "Longwinded": 8,
    "Confusing": 5
  },
  "slug": "charles_hazlewood",
  "thumbnail": "https://pi.tedcdn.com/r/pe.tedcdn.com/images/ted/0ab896226649f56d65b23c843462fec9a8448e3e_800x600.jpg?quality=89&w=600",
  "title": "Trusting the ensemble",
  "url": "https://www.ted.com/talks/charles_hazlewood",
  "video": {
    "low": "http://download.ted.com/talks/CharlesHazlewood_2011G-light.mp4",
    "medium": "http://download.ted.com/talks/CharlesHazlewood_2011G.mp4",
    "high": "http://download.ted.com/talks/CharlesHazlewood_2011G-480p.mp4"
  },
  "viewCount": 471084,
  "year": "2011"
}