{
  "audio": "http://download.ted.com/talks/ChristopherPoole_2010.mp3",
  "author": "Christopher \"moot\" Poole\"",
  "dateFilmed": 1265967300,
  "datePublished": 1275467340,
  "description": "The founder of 4chan, a controversial, uncensored online imageboard, describes its subculture, some of the Internet \"memes\" it has launched, and the incident in which its users managed a very public, precision hack of a mainstream media website. The talk raises questions about the power -- and price -- of anonymity.",
  "duration": 790,
  "event": "TED2010",
  "image": "https://pi.tedcdn.com/r/pe.tedcdn.com/images/ted/174869_800x600.jpg",
  "keywords": [
    "Internet",
    "TED Conference",
    "activism",
    "collaboration",
    "computers",
    "culture",
    "government",
    "law",
    "meme",
    "web"
  ],
  "mainLanguage": null,
  "objectID": 874,
  "otherLanguages": {
    "ar": "Arabic",
    "bg": "Bulgarian",
    "zh-cn": "Chinese, Simplified",
    "zh-tw": "Chinese, Traditional",
    "hr": "Croatian",
    "cs": "Czech",
    "nl": "Dutch",
    "en": "English",
    "fr": "French",
    "de": "German",
    "el": "Greek",
    "he": "Hebrew",
    "hu": "Hungarian",
    "it": "Italian",
    "ja": "Japanese",
    "ko": "Korean",
    "mk": "Macedonian",
    "nb": "Norwegian Bokmal",
    "pl": "Polish",
    "pt": "Portuguese",
    "pt-br": "Portuguese, Brazilian",
    "ro": "Romanian",
    "ru": "Russian",
    "sr": "Serbian",
    "sk": "Slovak",
    "es": "Spanish",
    "tr": "Turkish",
    "vi": "Vietnamese"
  },
  "ratings": {
    "Fascinating": 363,
    "Informative": 270,
    "Persuasive": 83,
    "Jaw-dropping": 80,
    "Ingenious": 145,
    "Funny": 441,
    "Inspiring": 159,
    "Confusing": 34,
    "Courageous": 238,
    "OK": 127,
    "Unconvincing": 88,
    "Beautiful": 36,
    "Longwinded": 14,
    "Obnoxious": 36
  },
  "slug": "christopher_m00t_poole_the_case_for_anonymity_online",
  "thumbnail": "https://pi.tedcdn.com/r/pe.tedcdn.com/images/ted/174869_800x600.jpg?quality=89&w=600",
  "title": "The case for anonymity online",
  "url": "https://www.ted.com/talks/christopher_m00t_poole_the_case_for_anonymity_online",
  "video": {
    "low": "http://download.ted.com/talks/ChristopherPoole_2010-light.mp4",
    "medium": "http://download.ted.com/talks/ChristopherPoole_2010.mp4",
    "high": "http://download.ted.com/talks/ChristopherPoole_2010-480p.mp4"
  },
  "viewCount": 1371355,
  "year": "2010"
}