{
  "audio": null,
  "author": "Chris Jordan",
  "dateFilmed": 1201910400,
  "datePublished": 1213563600,
  "description": "Artist Chris Jordan shows us an arresting view of what Western culture looks like. His supersized images picture some almost unimaginable statistics -- like the astonishing number of paper cups we use every single day.",
  "duration": 674,
  "event": "TED2008",
  "image": "https://pi.tedcdn.com/r/pe.tedcdn.com/images/ted/3ab72ed2ef7ef006f39a4ee8894cf41890f73ff5_1600x1200.jpg",
  "keywords": [
    "TED Conference",
    "art",
    "arts",
    "beauty",
    "business",
    "culture",
    "photography",
    "plastic",
    "statistics"
  ],
  "mainLanguage": null,
  "objectID": 279,
  "otherLanguages": {
    "ar": "Arabic",
    "bg": "Bulgarian",
    "zh-cn": "Chinese, Simplified",
    "zh-tw": "Chinese, Traditional",
    "nl": "Dutch",
    "en": "English",
    "et": "Estonian",
    "fr": "French",
    "de": "German",
    "he": "Hebrew",
    "it": "Italian",
    "ja": "Japanese",
    "ko": "Korean",
    "lt": "Lithuanian",
    "rup": "Macedo",
    "nb": "Norwegian Bokmal",
    "fa": "Persian",
    "pl": "Polish",
    "pt-br": "Portuguese, Brazilian",
    "ro": "Romanian",
    "sr": "Serbian",
    "sk": "Slovak",
    "es": "Spanish",
    "sv": "Swedish",
    "th": "Thai",
    "uk": "Ukrainian"
  },
  "ratings": {
    "Obnoxious": 73,
    "OK": 123,
    "Ingenious": 298,
    "Funny": 13,
    "Informative": 739,
    "Persuasive": 694,
    "Inspiring": 797,
    "Jaw-dropping": 502,
    "Fascinating": 547,
    "Courageous": 382,
    "Unconvincing": 105,
    "Beautiful": 221,
    "Longwinded": 75,
    "Confusing": 11
  },
  "slug": "chris_jordan_pictures_some_shocking_stats",
  "thumbnail": "https://pi.tedcdn.com/r/pe.tedcdn.com/images/ted/3ab72ed2ef7ef006f39a4ee8894cf41890f73ff5_1600x1200.jpg?quality=89&w=600",
  "title": "Turning powerful stats into art",
  "url": "https://www.ted.com/talks/chris_jordan_pictures_some_shocking_stats",
  "video": {
    "low": "http://download.ted.com/talks/ChrisJordan_2008-light.mp4",
    "medium": "http://download.ted.com/talks/ChrisJordan_2008.mp4",
    "high": "http://download.ted.com/talks/ChrisJordan_2008-480p.mp4"
  },
  "viewCount": 1314949,
  "year": "2008"
}