{
  "audio": "http://download.ted.com/talks/DanielWolpert_2011G.mp3",
  "author": "Daniel Wolpert",
  "dateFilmed": 1310515200,
  "datePublished": 1320332130,
  "description": "Neuroscientist Daniel Wolpert starts from a surprising premise: the brain evolved, not to think or feel, but to control movement. In this entertaining, data-rich talk he gives us a glimpse into how the brain creates the grace and agility of human motion.",
  "duration": 1199,
  "event": "TEDGlobal 2011",
  "image": "https://pi.tedcdn.com/r/pe.tedcdn.com/images/ted/794a93b76d7c657c2eb52e229c4b20e583615e06_1600x1200.jpg",
  "keywords": [
    "biology",
    "brain",
    "evolution",
    "neurology",
    "science"
  ],
  "mainLanguage": null,
  "objectID": 1261,
  "otherLanguages": {
    "ar": "Arabic",
    "bg": "Bulgarian",
    "zh-cn": "Chinese, Simplified",
    "zh-tw": "Chinese, Traditional",
    "hr": "Croatian",
    "cs": "Czech",
    "nl": "Dutch",
    "en": "English",
    "fr": "French",
    "de": "German",
    "el": "Greek",
    "he": "Hebrew",
    "hu": "Hungarian",
    "it": "Italian",
    "ja": "Japanese",
    "ko": "Korean",
    "mk": "Macedonian",
    "fa": "Persian",
    "pl": "Polish",
    "pt": "Portuguese",
    "pt-br": "Portuguese, Brazilian",
    "ro": "Romanian",
    "ru": "Russian",
    "sr": "Serbian",
    "sk": "Slovak",
    "es": "Spanish",
    "th": "Thai",
    "tr": "Turkish",
    "uk": "Ukrainian",
    "vi": "Vietnamese"
  },
  "ratings": {
    "Fascinating": 649,
    "Informative": 548,
    "Funny": 105,
    "Beautiful": 38,
    "Longwinded": 73,
    "Persuasive": 194,
    "Ingenious": 175,
    "Obnoxious": 16,
    "Unconvincing": 53,
    "OK": 55,
    "Confusing": 55,
    "Jaw-dropping": 67,
    "Inspiring": 133,
    "Courageous": 12
  },
  "slug": "daniel_wolpert_the_real_reason_for_brains",
  "thumbnail": "https://pi.tedcdn.com/r/pe.tedcdn.com/images/ted/794a93b76d7c657c2eb52e229c4b20e583615e06_1600x1200.jpg?quality=89&w=600",
  "title": "The real reason for brains",
  "url": "https://www.ted.com/talks/daniel_wolpert_the_real_reason_for_brains",
  "video": {
    "low": "http://download.ted.com/talks/DanielWolpert_2011G-light.mp4",
    "medium": "http://download.ted.com/talks/DanielWolpert_2011G.mp4",
    "high": "http://download.ted.com/talks/DanielWolpert_2011G-480p.mp4"
  },
  "viewCount": 1620099,
  "year": "2011"
}