{
  "audio": "http://download.ted.com/talks/JuliaBacha_2011G.mp3",
  "author": "Julia Bacha",
  "dateFilmed": 1310515200,
  "datePublished": 1314803416,
  "description": "In 2003, the Palestinian village of Budrus mounted a 10-month-long nonviolent protest to stop a barrier being built across their olive groves. Did you hear about it? Didn't think so. Brazilian filmmaker Julia Bacha asks why we only pay attention to violence in the Israel-Palestine conflict -- and not to the nonviolent leaders who may one day bring peace.",
  "duration": 651,
  "event": "TEDGlobal 2011",
  "image": "https://pi.tedcdn.com/r/pe.tedcdn.com/images/ted/f67f17e1df4e8d46cdddc96c2ddd77b03128e49d_800x600.jpg",
  "keywords": [
    "arts",
    "communication",
    "compassion",
    "entertainment",
    "film",
    "peace",
    "violence",
    "war"
  ],
  "mainLanguage": null,
  "objectID": 1214,
  "otherLanguages": {
    "sq": "Albanian",
    "ar": "Arabic",
    "bg": "Bulgarian",
    "ca": "Catalan",
    "zh-cn": "Chinese, Simplified",
    "zh-tw": "Chinese, Traditional",
    "hr": "Croatian",
    "cs": "Czech",
    "nl": "Dutch",
    "en": "English",
    "fr": "French",
    "fr-ca": "French (Canada)",
    "de": "German",
    "el": "Greek",
    "he": "Hebrew",
    "hu": "Hungarian",
    "id": "Indonesian",
    "it": "Italian",
    "ja": "Japanese",
    "ko": "Korean",
    "mk": "Macedonian",
    "fa": "Persian",
    "pl": "Polish",
    "pt": "Portuguese",
    "pt-br": "Portuguese, Brazilian",
    "ro": "Romanian",
    "ru": "Russian",
    "sr": "Serbian",
    "es": "Spanish",
    "th": "Thai",
    "tr": "Turkish",
    "uk": "Ukrainian",
    "vi": "Vietnamese"
  },
  "ratings": {
    "Inspiring": 676,
    "Persuasive": 473,
    "Informative": 318,
    "Courageous": 324,
    "Ingenious": 35,
    "Fascinating": 80,
    "Funny": 7,
    "Longwinded": 14,
    "Unconvincing": 73,
    "Confusing": 14,
    "Obnoxious": 45,
    "Jaw-dropping": 57,
    "Beautiful": 112,
    "OK": 35
  },
  "slug": "julia_bacha",
  "thumbnail": "https://pi.tedcdn.com/r/pe.tedcdn.com/images/ted/f67f17e1df4e8d46cdddc96c2ddd77b03128e49d_800x600.jpg?quality=89&w=600",
  "title": "Pay attention to nonviolence",
  "url": "https://www.ted.com/talks/julia_bacha",
  "video": {
    "low": "http://download.ted.com/talks/JuliaBacha_2011G-light.mp4",
    "medium": "http://download.ted.com/talks/JuliaBacha_2011G.mp4",
    "high": "http://download.ted.com/talks/JuliaBacha_2011G-480p.mp4"
  },
  "viewCount": 667849,
  "year": "2011"
}