{
  "audio": null,
  "author": "Keith Nolan",
  "dateFilmed": 1303516800,
  "datePublished": 1329058599,
  "description": "Keith Nolan always wanted to join the United States military. The challenge: He is Deaf, which is an automatic disqualification according to military rules. In this talk, he describes his fight to fight for his country. (In American Sign Language, with real-time translation.)",
  "duration": 1121,
  "event": "TEDxIslay",
  "image": "https://pi.tedcdn.com/r/pe.tedcdn.com/images/ted/53b14f3d20e937e8801fca18d4ba57ef80ab860c_800x600.jpg",
  "keywords": [
    "TEDx",
    "disability",
    "global issues",
    "military"
  ],
  "mainLanguage": null,
  "objectID": 1354,
  "otherLanguages": {
  },
  "ratings": {
    "Fascinating": 50,
    "Courageous": 127,
    "Inspiring": 187,
    "Obnoxious": 9,
    "Beautiful": 31,
    "Longwinded": 10,
    "Unconvincing": 6,
    "Informative": 37,
    "Persuasive": 59,
    "Jaw-dropping": 21,
    "OK": 22,
    "Ingenious": 4,
    "Funny": 4,
    "Confusing": 0
  },
  "slug": "keith_nolan_deaf_in_the_military",
  "thumbnail": "https://pi.tedcdn.com/r/pe.tedcdn.com/images/ted/53b14f3d20e937e8801fca18d4ba57ef80ab860c_800x600.jpg?quality=89&w=600",
  "title": "Deaf in the military",
  "url": "https://www.ted.com/talks/keith_nolan_deaf_in_the_military",
  "video": {
    "youtube": {
      "id": "gtKTcPq7XBs",
      "url": "http://www.ted.com/tedx/events/1688"
    }
  },
  "viewCount": 100866,
  "year": "2011"
}