{
  "audio": "http://download.ted.com/talks/RoryStewart_2011G.mp3",
  "author": "Rory Stewart",
  "dateFilmed": 1310688000,
  "datePublished": 1311605760,
  "description": "British MP Rory Stewart walked across Afghanistan after 9/11, talking with citizens and warlords alike. Now, a decade later, he asks: Why are Western and coalition forces still fighting there? He shares lessons from past military interventions that worked -- Bosnia, for instance -- and shows that humility and local expertise are the keys to success.",
  "duration": 1202,
  "event": "TEDGlobal 2011",
  "image": "https://pi.tedcdn.com/r/pe.tedcdn.com/images/ted/7bb5389d0360ef7905de6b6a017b7ce836ad673d_800x600.jpg",
  "keywords": [
    "Foreign Policy",
    "Middle East",
    "global issues",
    "military",
    "peace",
    "politics",
    "war"
  ],
  "mainLanguage": null,
  "objectID": 1196,
  "otherLanguages": {
    "ar": "Arabic",
    "bg": "Bulgarian",
    "zh-cn": "Chinese, Simplified",
    "zh-tw": "Chinese, Traditional",
    "zh": "Chinese, Yue",
    "cs": "Czech",
    "nl": "Dutch",
    "en": "English",
    "fr": "French",
    "de": "German",
    "el": "Greek",
    "he": "Hebrew",
    "hi": "Hindi",
    "hu": "Hungarian",
    "id": "Indonesian",
    "it": "Italian",
    "ja": "Japanese",
    "ko": "Korean",
    "fa": "Persian",
    "pl": "Polish",
    "pt": "Portuguese",
    "pt-br": "Portuguese, Brazilian",
    "ro": "Romanian",
    "ru": "Russian",
    "sr": "Serbian",
    "sk": "Slovak",
    "es": "Spanish",
    "sv": "Swedish",
    "th": "Thai",
    "tr": "Turkish",
    "vi": "Vietnamese"
  },
  "ratings": {
    "Persuasive": 515,
    "Courageous": 206,
    "Inspiring": 178,
    "Informative": 313,
    "Fascinating": 113,
    "Unconvincing": 48,
    "Ingenious": 38,
    "Beautiful": 11,
    "Jaw-dropping": 50,
    "Longwinded": 13,
    "Obnoxious": 14,
    "OK": 19,
    "Confusing": 9,
    "Funny": 4
  },
  "slug": "rory_stewart_time_to_end_the_war_in_afghanistan",
  "thumbnail": "https://pi.tedcdn.com/r/pe.tedcdn.com/images/ted/7bb5389d0360ef7905de6b6a017b7ce836ad673d_800x600.jpg?quality=89&w=600",
  "title": "Time to end the war in Afghanistan",
  "url": "https://www.ted.com/talks/rory_stewart_time_to_end_the_war_in_afghanistan",
  "video": {
    "low": "http://download.ted.com/talks/RoryStewart_2011G-light.mp4",
    "medium": "http://download.ted.com/talks/RoryStewart_2011G.mp4",
    "high": "http://download.ted.com/talks/RoryStewart_2011G-480p.mp4"
  },
  "viewCount": 634746,
  "year": "2011"
}