{
  "audio": null,
  "author": "Virginia Postrel",
  "dateFilmed": 1075680000,
  "datePublished": 1224136740,
  "description": "In a timely talk, cultural critic Virginia Postrel muses on the true meaning, and the powerful uses, of glamour -- which she defines as any calculated, carefully polished image designed to impress and persuade. ",
  "duration": 975,
  "event": "TED2004",
  "image": "https://pi.tedcdn.com/r/pe.tedcdn.com/images/ted/56319_480x360.jpg",
  "keywords": [
    "TED Conference",
    "beauty",
    "business",
    "culture",
    "entertainment",
    "illusion",
    "marketing",
    "performance",
    "politics"
  ],
  "mainLanguage": null,
  "objectID": 375,
  "otherLanguages": {
    "ar": "Arabic",
    "hy": "Armenian",
    "bg": "Bulgarian",
    "zh-cn": "Chinese, Simplified",
    "zh-tw": "Chinese, Traditional",
    "nl": "Dutch",
    "en": "English",
    "fr": "French",
    "de": "German",
    "he": "Hebrew",
    "it": "Italian",
    "ja": "Japanese",
    "ko": "Korean",
    "lt": "Lithuanian",
    "pl": "Polish",
    "pt-br": "Portuguese, Brazilian",
    "ro": "Romanian",
    "ru": "Russian",
    "sr": "Serbian",
    "es": "Spanish",
    "tr": "Turkish"
  },
  "ratings": {
    "Longwinded": 84,
    "Obnoxious": 68,
    "Informative": 169,
    "Funny": 28,
    "Fascinating": 81,
    "Persuasive": 51,
    "Unconvincing": 61,
    "OK": 98,
    "Beautiful": 38,
    "Jaw-dropping": 7,
    "Ingenious": 20,
    "Confusing": 27,
    "Courageous": 8,
    "Inspiring": 31
  },
  "slug": "virginia_postrel_on_glamour",
  "thumbnail": "https://pi.tedcdn.com/r/pe.tedcdn.com/images/ted/56319_480x360.jpg?quality=89&w=600",
  "title": "On glamour",
  "url": "https://www.ted.com/talks/virginia_postrel_on_glamour",
  "video": {
    "low": "http://download.ted.com/talks/VirginiaPostrel_2004-light.mp4",
    "medium": "http://download.ted.com/talks/VirginiaPostrel_2004.mp4",
    "high": "http://download.ted.com/talks/VirginiaPostrel_2004-480p.mp4"
  },
  "viewCount": 354503,
  "year": "2004"
}