{
  "audio": "http://download.ted.com/talks/WillPotter_2015F.mp3",
  "author": "Will Potter",
  "dateFilmed": 1440720000,
  "datePublished": 1445266800,
  "description": "Investigative journalist Will Potter is the only reporter who has been inside a Communications Management Unit, or CMU, within a US prison. These units were opened secretly, and radically alter how prisoners are treated -- even preventing them from hugging their children. Potter, a TED Fellow, shows us who is imprisoned here, and how the government is trying to keep them hidden. \"The message was clear,\" he says. \"Don’t talk about this place.\" Find sources for this talk at  willpotter.com/cmu",
  "duration": 895,
  "event": "TED Fellows Retreat 2015",
  "image": "https://pi.tedcdn.com/r/pe.tedcdn.com/images/ted/a1f6ba3d17e6e9d7404ee1ff61546579c2126b52_2880x1620.jpg",
  "keywords": [
    "TED Fellows",
    "communication",
    "crime",
    "journalism",
    "prison",
    "privacy"
  ],
  "mainLanguage": null,
  "objectID": 2352,
  "otherLanguages": {
    "uk": "Ukrainian"
  },
  "ratings": {
    "Courageous": 442,
    "Informative": 409,
    "Inspiring": 134,
    "Jaw-dropping": 128,
    "Fascinating": 96,
    "Obnoxious": 37,
    "Unconvincing": 29,
    "OK": 48,
    "Persuasive": 84,
    "Ingenious": 11,
    "Longwinded": 17,
    "Beautiful": 6,
    "Funny": 11,
    "Confusing": 6
  },
  "slug": "will_potter_the_secret_us_prisons_you_ve_never_heard_of_before",
  "thumbnail": "https://pi.tedcdn.com/r/pe.tedcdn.com/images/ted/a1f6ba3d17e6e9d7404ee1ff61546579c2126b52_2880x1620.jpg?quality=89&w=600",
  "title": "The secret US prisons you've never heard of before",
  "url": "https://www.ted.com/talks/will_potter_the_secret_us_prisons_you_ve_never_heard_of_before",
  "video": {
    "low": "http://download.ted.com/talks/WillPotter_2015F-light.mp4",
    "medium": "http://download.ted.com/talks/WillPotter_2015F.mp4"
  },
  "viewCount": 1775310,
  "year": "2015"
}