{
  "id": 1114,
  "name": "Morgan Spurlock: The greatest TED Talk ever sold",
  "speakers": [
    "Morgan Spurlock"
  ],
  "description": "With humor and persistence, filmmaker Morgan Spurlock dives into the hidden but influential world of brand marketing, on his quest to make a completely sponsored film about sponsorship. (And yes, onstage naming rights for this talk were sponsored too. By whom and for how much? He'll tell you.)",
  "slug": "morgan_spurlock_the_greatest_ted_talk_ever_sold",
  "date": "2011-03-02T00:00:00+00:00",
  "event": "TED2011",
  "url": null,
  "tags": [
    "Brand",
    "business",
    "consumerism",
    "film",
    "humor"
  ]
}