{
  "id": 1135,
  "name": "Arvind Gupta: Turning trash into toys for learning",
  "speakers": [
    "Arvind Gupta"
  ],
  "description": "At the INK Conference, Arvind Gupta shares simple yet stunning plans for turning trash into seriously entertaining, well-designed toys that kids can build themselves -- while learning basic principles of science and design. ",
  "slug": "arvind_gupta_turning_trash_into_toys_for_learning",
  "date": "2010-12-09T00:00:00+00:00",
  "event": "INK Conference",
  "url": "http://download.ted.com/talks/ArvindGupta_2010P.mp3?apikey=4be802cf69ff655f353d0e541e087ef680ae68e2",
  "tags": [
    "design",
    "education",
    "play",
    "science",
    "technology",
    "toy"
  ]
}