{
  "id": 1230,
  "name": "Sunni Brown: Doodlers, unite!",
  "speakers": [
    "Sunni Brown"
  ],
  "description": "Studies show that sketching and doodling improve our comprehension -- and our creative thinking. So why do we still feel embarrassed when we're caught doodling in a meeting? Sunni Brown says: Doodlers, unite! She makes the case for unlocking your brain via pad and pen.",
  "slug": "sunni_brown",
  "date": "2011-03-03T00:00:00+00:00",
  "event": "TED2011",
  "url": null,
  "tags": [
    "business",
    "creativity",
    "culture",
    "presentation"
  ]
}