{
  "id": 1297,
  "name": "Yoav Medan: Ultrasound surgery -- healing without cuts",
  "speakers": [
    "Yoav Medan"
  ],
  "description": "Imagine having a surgery with no knives involved. At TEDMED, Yoav Medan shares a technique that uses MRI to find trouble spots and focused ultrasound to treat such issues as brain lesions, uterine fibroids and several kinds of cancerous growths.",
  "slug": "yoav_medan_ultrasound_surgery_healing_without_cuts",
  "date": "2011-10-24T00:00:00+00:00",
  "event": "TEDMED 2011",
  "url": null,
  "tags": [
    "health care",
    "medical research",
    "medicine",
    "science",
    "technology"
  ]
}