{
  "id": 1302,
  "name": "Quyen Nguyen: Color-coded surgery",
  "speakers": [
    "Quyen Nguyen"
  ],
  "description": "Surgeons are taught from textbooks which conveniently color-code the types of tissues, but that's not what it looks like in real life -- until now. At TEDMED Quyen Nguyen demonstrates how a molecular marker can make tumors light up in neon green, showing surgeons exactly where to cut.",
  "slug": "quyen_nguyen_color_coded_surgery",
  "date": "2011-10-28T00:00:00+00:00",
  "event": "TEDMED 2011",
  "url": null,
  "tags": [
    "cancer",
    "medicine",
    "science",
    "technology"
  ]
}