{
  "id": 1457,
  "name": "Shereen El-Feki: HIV -- how to fight an epidemic of bad laws",
  "speakers": [
    "Shereen El Feki"
  ],
  "description": "There is an epidemic of HIV, and with it an epidemic of bad laws -- laws that effectively criminalize being HIV positive. At the TEDxSummit in Doha, TED Fellow Shereen El-Feki gives a forceful argument that these laws, based in stigma, are actually helping the disease spread.",
  "slug": "shereen_el_feki_how_to_fight_an_epidemic_of_bad_laws",
  "date": "2012-04-18T00:00:00+00:00",
  "event": "TEDxSummit",
  "url": "http://download.ted.com/talks/ShereenElFeki_2012S.mp3?apikey=4be802cf69ff655f353d0e541e087ef680ae68e2",
  "tags": [
    "AIDS",
    "TEDx",
    "global issues",
    "health",
    "law"
  ]
}