{
  "id": 1533,
  "name": "Margaret Heffernan: Dare to disagree",
  "speakers": [
    "Margaret Heffernan"
  ],
  "description": "Most people instinctively avoid conflict, but as Margaret Heffernan shows us, good disagreement is central to progress. She illustrates (sometimes counterintuitively) how the best partners aren’t echo chambers -- and how great research teams, relationships and businesses allow people to deeply disagree.",
  "slug": "margaret_heffernan_dare_to_disagree",
  "date": "2012-06-29T00:00:00+00:00",
  "event": "TEDGlobal 2012",
  "url": "http://download.ted.com/talks/MargaretHeffernan_2012G.mp3?apikey=4be802cf69ff655f353d0e541e087ef680ae68e2",
  "tags": [
    "business",
    "leadership",
    "women in business"
  ]
}