{
  "id": 1646,
  "name": "Angela Patton: A father-daughter dance ... in prison",
  "speakers": [
    "Angela Patton"
  ],
  "description": "At Camp Diva, Angela Patton works to help girls and fathers stay connected and in each others' lives. But what about girls whose fathers can't be there -- because they're in jail? Patton tells the story of a very special father-daughter dance. <em>(Filmed at TEDxWomen)</em>",
  "slug": "angela_patton_a_father_daughter_dance_in_prison",
  "date": "2012-11-30T00:00:00+00:00",
  "event": "TEDxWomen 2012",
  "url": null,
  "tags": [
    "TEDx",
    "activism",
    "children",
    "dance",
    "parenting",
    "social change",
    "women",
    "youth"
  ]
}