{
  "id": 1726,
  "name": "Nilofer Merchant: Got a meeting? Take a walk",
  "speakers": [
    "Nilofer Merchant"
  ],
  "description": "Nilofer Merchant suggests a small idea that just might have a big impact on your life and health: Next time you have a one-on-one meeting, make it into a \"walking meeting\" -- and let ideas flow while you walk and talk.",
  "slug": "nilofer_merchant_got_a_meeting_take_a_walk",
  "date": "2013-02-26T00:00:00+00:00",
  "event": "TED2013",
  "url": "http://download.ted.com/talks/NiloferMerchant_2013.mp3?apikey=4be802cf69ff655f353d0e541e087ef680ae68e2",
  "tags": [
    "business",
    "communication",
    "health"
  ]
}