{
  "id": 1808,
  "name": "Derek Paravicini and Adam Ockelford: In the key of genius",
  "speakers": [
    "Derek Paravicini",
    "Adam Ockelford"
  ],
  "description": "Born three and a half months prematurely, Derek Paravicini is blind and has severe autism. But with perfect pitch, innate talent and a lot of practice, he became an acclaimed concert pianist by the age of 10. Here, his longtime piano teacher, Adam Ockelford, explains his student’s unique relationship to music, while Paravicini shows how he has ripped up the \"Chopsticks\" rule book. (<em>Filmed at TEDxWarwick.</em>)",
  "slug": "derek_paravicini_and_adam_ockelford_in_the_key_of_genius",
  "date": "2013-03-01T00:00:00+00:00",
  "event": "TEDxWarwick",
  "url": "http://download.ted.com/talks/AdamOckelford_2013X.mp3?apikey=4be802cf69ff655f353d0e541e087ef680ae68e2",
  "tags": [
    "TEDx",
    "disability",
    "live music",
    "music"
  ]
}