{
  "id": 1925,
  "name": "Yann Dall'Aglio: Love -- you're doing it wrong",
  "speakers": [
    "Yann Dall'Aglio"
  ],
  "description": "In this delightful talk, philosopher Yann Dall’Aglio explores the universal search for tenderness and connection in a world that's ever more focused on the individual. As it turns out, it's easier than you think. A wise and witty reflection on the state of love in the modern age. <i>(Filmed at TEDxParis.)</I>",
  "slug": "yann_dall_aglio_love_you_re_doing_it_wrong",
  "date": "2012-10-12T00:00:00+00:00",
  "event": "TEDxParis 2012",
  "url": null,
  "tags": [
    "TEDx",
    "culture",
    "love",
    "philosophy"
  ]
}