{
  "id": 219,
  "name": "Moshe Safdie: Building uniqueness",
  "speakers": [
    "Moshe Safdie"
  ],
  "description": "Looking back over his long career, architect Moshe Safdie delves into four of his design projects and explains how he labored to make each one truly unique for its site and its users.",
  "slug": "moshe_safdie_on_building_uniqueness",
  "date": "2002-03-03T00:00:00+00:00",
  "event": "TED2002",
  "url": null,
  "tags": [
    "architecture",
    "cities",
    "collaboration",
    "creativity",
    "design",
    "museums",
    "visualizations"
  ]
}