{
  "id": 537,
  "name": "Louise Fresco: We need to feed the whole world",
  "speakers": [
    "Louise Fresco"
  ],
  "description": "Louise Fresco shows us why we should celebrate mass-produced, supermarket-style white bread. She says environmentally sound mass production will feed the world, yet leave a role for small bakeries and traditional methods.",
  "slug": "louise_fresco_on_feeding_the_whole_world",
  "date": "2009-02-05T15:40:00+00:00",
  "event": "TED2009",
  "url": null,
  "tags": [
    "business",
    "development",
    "food",
    "global issues",
    "industrial design"
  ]
}