{
  "id": 618,
  "name": "Dan Pink: The puzzle of motivation",
  "speakers": [
    "Dan Pink"
  ],
  "description": "Career analyst Dan Pink examines the puzzle of motivation, starting with a fact that social scientists know but most managers don't: Traditional rewards aren't always as effective as we think. Listen for illuminating stories -- and maybe, a way forward.",
  "slug": "dan_pink_on_motivation",
  "date": "2009-07-24T00:00:00+00:00",
  "event": "TEDGlobal 2009",
  "url": "http://download.ted.com/talks/DanielPink_2009G.mp3?apikey=4be802cf69ff655f353d0e541e087ef680ae68e2",
  "tags": [
    "brain",
    "business",
    "creativity",
    "motivation",
    "science",
    "social change",
    "work"
  ]
}