{
  "id": 619,
  "name": "Eric Giler: A demo of wireless electricity",
  "speakers": [
    "Eric Giler"
  ],
  "description": "Eric Giler wants to untangle our wired lives with cable-free electric power. Here, he covers what this sci-fi tech offers, and demos MIT's breakthrough version, WiTricity -- a near-to-market invention that may soon recharge your cell phone, car, pacemaker.",
  "slug": "eric_giler_demos_wireless_electricity",
  "date": "2009-07-23T00:00:00+00:00",
  "event": "TEDGlobal 2009",
  "url": null,
  "tags": [
    "engineering",
    "entrepreneur",
    "future",
    "science",
    "technology"
  ]
}