{
  "id": 883,
  "name": "David Byrne: How architecture helped music evolve",
  "speakers": [
    "David Byrne"
  ],
  "description": "As his career grew, David Byrne went from playing CBGB to Carnegie Hall. He asks: Does the venue make the music? From outdoor drumming to Wagnerian operas to arena rock, he explores how context has pushed musical innovation.",
  "slug": "david_byrne_how_architecture_helped_music_evolve",
  "date": "2010-02-12T10:16:00+00:00",
  "event": "TED2010",
  "url": "http://download.ted.com/talks/DavidByrne_2010.mp3?apikey=4be802cf69ff655f353d0e541e087ef680ae68e2",
  "tags": [
    "architecture",
    "arts",
    "future",
    "history",
    "music"
  ]
}