{
  "id": 885,
  "name": "Margaret Gould Stewart: How YouTube thinks about copyright",
  "speakers": [
    "Margaret Gould Stewart"
  ],
  "description": "Margaret Gould Stewart, YouTube's head of user experience, talks about how the ubiquitous video site works with copyright holders and creators to foster (at the best of times) a creative ecosystem where everybody wins.",
  "slug": "margaret_stewart_how_youtube_thinks_about_copyright",
  "date": "2010-02-10T00:00:00+00:00",
  "event": "TED2010",
  "url": "http://download.ted.com/talks/MargaretStewart_2010U.mp3?apikey=4be802cf69ff655f353d0e541e087ef680ae68e2",
  "tags": [
    "art",
    "arts",
    "business",
    "creativity",
    "culture",
    "entertainment",
    "law",
    "online video",
    "technology"
  ]
}