{
  "id": 963,
  "name": "Annie Lennox: Why I am an HIV/AIDS activist",
  "speakers": [
    "Annie Lennox"
  ],
  "description": "For the last eight years, pop singer Annie Lennox has devoted the majority of her time to her SING campaign, raising awareness and money to combat HIV/AIDS. She shares the experiences that have inspired her, from working with Nelson Mandela to meeting a little African girl in a desperate situation.\r\n",
  "slug": "annie_lennox_why_i_am_an_hiv_aids_activist",
  "date": "2010-07-15T10:05:00+00:00",
  "event": "TEDGlobal 2010",
  "url": "http://download.ted.com/talks/AnnieLennox_2010G.mp3?apikey=4be802cf69ff655f353d0e541e087ef680ae68e2",
  "tags": [
    "AIDS",
    "Africa",
    "activism",
    "health",
    "personal growth"
  ]
}