{
  "id": 972,
  "name": "Tim Jackson: An economic reality check",
  "speakers": [
    "Tim Jackson"
  ],
  "description": "As the world faces recession, climate change, inequity and more, Tim Jackson delivers a piercing challenge to established economic principles, explaining how we might stop feeding the crises and start investing in our future.",
  "slug": "tim_jackson_s_economic_reality_check",
  "date": "2010-07-15T00:00:00+00:00",
  "event": "TEDGlobal 2010",
  "url": "http://download.ted.com/talks/TimJackson_2010G.mp3?apikey=4be802cf69ff655f353d0e541e087ef680ae68e2",
  "tags": [
    "development",
    "economics",
    "green",
    "poverty",
    "sustainability"
  ]
}